tests/__init__.py
tests/conftest.py
tests/test_cassandra.py
tests/test_controller.py
tests/test_db.py
tests/test_exception.py
tests/test_extra.py
tests/test_locks.py
tests/test_mysql.py
tests/test_pattern.py
tests/test_postgres.py
tests/test_queue.py
tests/test_redis.py
tests/test_schema.py
tests/test_secure_token.py
tornado_battery/__init__.py
tornado_battery/cassandra.py
tornado_battery/command.py
tornado_battery/controller.py
tornado_battery/db.py
tornado_battery/disable_tornado_logging_options.py
tornado_battery/entry.py
tornado_battery/exception.py
tornado_battery/extra.py
tornado_battery/locks.py
tornado_battery/logging.py
tornado_battery/mysql.py
tornado_battery/pattern.py
tornado_battery/postgres.py
tornado_battery/queue.py
tornado_battery/redis.py
tornado_battery/route.py
tornado_battery/schema.py
tornado_battery/secure_token.py
tornado_battery-0.8.1.dist-info/METADATA
tornado_battery-0.8.1.dist-info/WHEEL
tornado_battery-0.8.1.dist-info/top_level.txt
tornado_battery-0.8.1.dist-info/RECORD
