Metadata-Version: 2.1
Name: tornado-battery
Version: 0.8.1
Summary: utilities that help write tornado apps quickly and easily
Home-page: https://github.com/jianingy/tornado_battery
Author: UNKNOWN
Author-email: UNKNOWN
License: UNKNOWN
Platform: UNKNOWN
Requires-Dist: aio-pika (==5.2.4)
Requires-Dist: aiocassandra (==2.0.1)
Requires-Dist: aiomysql (==0.0.20)
Requires-Dist: aiopg (==0.16.0)
Requires-Dist: aioredis (==1.2.0)
Requires-Dist: aiormq (==1.2.2)
Requires-Dist: asn1crypto (==0.24.0)
Requires-Dist: async-generator (==1.10)
Requires-Dist: async-timeout (==3.0.1)
Requires-Dist: asyncio-extras (==1.3.2)
Requires-Dist: cassandra-driver (==3.17.0)
Requires-Dist: cffi (==1.12.2)
Requires-Dist: colorlog (==4.0.2)
Requires-Dist: cryptography (==2.5)
Requires-Dist: hiredis (==1.0.0)
Requires-Dist: idna (==2.8)
Requires-Dist: marshmallow (==2.18.1)
Requires-Dist: multidict (==4.5.2)
Requires-Dist: pamqp (==2.1.0)
Requires-Dist: peewee-async (==0.5.12)
Requires-Dist: peewee (==2.10.2)
Requires-Dist: psycopg2-binary (==2.7.7)
Requires-Dist: pycparser (==2.19)
Requires-Dist: pycrypto (==2.6.1)
Requires-Dist: pymysql (==0.9.2)
Requires-Dist: six (==1.12.0)
Requires-Dist: tornado (==5.1.1)
Requires-Dist: ujson (==1.35)
Requires-Dist: yarl (==1.3.0)
